aucodb/__init__.py
aucodb/client/__init__.py
aucodb/client/auco_client.py
aucodb/database/__init__.py
aucodb/database/aucodb.py
aucodb/graph/__init__.py
aucodb/graph/data.jsonl
aucodb/graph/llm_graph_transformer.py
aucodb/graph/neo4j_client.py
aucodb/server/__init__.py
aucodb/server/auco_server.py
aucodb/vectordb/__init__.py
aucodb/vectordb/configs.yaml
aucodb/vectordb/factory.py
aucodb/vectordb/processor/__init__.py
aucodb/vectordb/processor/processor.py
aucodb/vectordb/providers/__init__.py
aucodb/vectordb/providers/base.py
aucodb/vectordb/providers/chromadb.py
aucodb/vectordb/providers/faiss.py
aucodb/vectordb/providers/milvus.py
aucodb/vectordb/providers/pgvector.py
aucodb/vectordb/providers/pinecone.py
aucodb/vectordb/providers/qdrant.py
aucodb/vectordb/providers/weaviate.py
aucodb/vectordb/requirements.txt
aucodb-0.1.8.dist-info/LICENSE
aucodb-0.1.8.dist-info/METADATA
aucodb-0.1.8.dist-info/WHEEL
aucodb-0.1.8.dist-info/RECORD
