Metadata-Version: 2.3
Name: aucodb
Version: 0.1.8
Summary: No-SQL Documented Collection Database
Author: phamdinhkhanh
Author-email: phamdinhkhanh.tkt53.neu@gmail.com
Requires-Python: >=3.10,<3.14
Classifier: Programming Language :: Python :: 3
Classifier: Programming Language :: Python :: 3.10
Classifier: Programming Language :: Python :: 3.11
Classifier: Programming Language :: Python :: 3.12
Classifier: Programming Language :: Python :: 3.13
Provides-Extra: graph
Provides-Extra: vectordb
Requires-Dist: aiofiles (==24.1.0)
Requires-Dist: fastapi (>=0.115.0,<0.116.0)
Requires-Dist: ipykernel (==6.29.5)
Requires-Dist: langchain (==0.3.25) ; extra == "vectordb"
Requires-Dist: langchain-community (==0.3.23) ; extra == "vectordb"
Requires-Dist: langchain-core (==0.3.59) ; extra == "vectordb"
Requires-Dist: langchain-huggingface (==0.2.0) ; extra == "vectordb"
Requires-Dist: langchain-milvus (==0.1.10) ; extra == "vectordb"
Requires-Dist: langchain-openai (==0.3.16) ; extra == "vectordb"
Requires-Dist: langchain-pinecone (==0.2.6) ; extra == "vectordb"
Requires-Dist: langchain-text-splitters (==0.3.8) ; extra == "vectordb"
Requires-Dist: neo4j (==5.28.1) ; extra == "graph"
Requires-Dist: pinecone (==6.0.2) ; extra == "vectordb"
Requires-Dist: pinecone-client (==6.0.0) ; extra == "vectordb"
Requires-Dist: pinecone-plugin-interface (==0.0.7) ; extra == "vectordb"
Requires-Dist: pydantic (>=2.0,<3.0)
Requires-Dist: pymilvus (==2.5.8) ; extra == "vectordb"
Requires-Dist: pyvis (==0.3.2) ; extra == "graph"
Requires-Dist: requests (==2.32.3)
Requires-Dist: uvicorn (>=0.22.0)
